[{"domain": ".bilibili.com", "expiry": 1723687593, "httpOnly": false, "name": "buvid4", "path": "/", "sameSite": "Lax", "secure": false, "value": "87FCF8C3-7494-9F3E-D04E-1D9C6A95D19A81071-023071210-qndugPdHbDeY1dNOgdssSw%3D%3D"}, {"domain": ".bilibili.com", "expiry": 1720663592, "httpOnly": false, "name": "header_theme_version", "path": "/", "sameSite": "Lax", "secure": false, "value": "CLOSE"}, {"domain": ".bilibili.com", "expiry": 1704679591, "httpOnly": false, "name": "DedeUserID__ckMd5", "path": "/", "sameSite": "Lax", "secure": false, "value": "0ad6fdaf7a688b2d"}, {"domain": ".bilibili.com", "expiry": 1704679591, "httpOnly": false, "name": "DedeUserID", "path": "/", "sameSite": "Lax", "secure": false, "value": "273084021"}, {"domain": ".bilibili.com", "expiry": 1704679591, "httpOnly": true, "name": "SESSDATA", "path": "/", "sameSite": "Lax", "secure": true, "value": "4cb78d36%2C1704679591%2Ce4806%2A72XRNfYdNDALTgulCykjgJTs7j_NucgGbhRvFUqH8Ae6Y9omAtFp8kixwfL-FOuBnn5GmAEAAAFQA"}, {"domain": ".bilibili.com", "expiry": 1704679591, "httpOnly": false, "name": "sid", "path": "/", "sameSite": "Lax", "secure": false, "value": "88h24ooo"}, {"domain": ".bilibili.com", "expiry": 1689128188, "httpOnly": false, "name": "csrf_state", "path": "/", "sameSite": "Lax", "secure": false, "value": "0f0bd1d1466502cc0f0b61d93a78ac61"}, {"domain": ".bilibili.com", "expiry": 1723687581, "httpOnly": false, "name": "buvid_fp", "path": "/", "sameSite": "Lax", "secure": false, "value": "87f69c4015ceda52da59286e92f6abb0"}, {"domain": ".bilibili.com", "expiry": 1720663592, "httpOnly": false, "name": "FEED_LIVE_VERSION", "path": "/", "sameSite": "Lax", "secure": false, "value": "V8"}, {"domain": ".bilibili.com", "expiry": 1720663579, "httpOnly": false, "name": "b_nut", "path": "/", "sameSite": "Lax", "secure": false, "value": "1689127580"}, {"domain": ".bilibili.com", "expiry": 1720663592, "httpOnly": false, "name": "browser_resolution", "path": "/", "sameSite": "Lax", "secure": false, "value": "1536-748"}, {"domain": ".bilibili.com", "expiry": 1720663592, "httpOnly": false, "name": "home_feed_column", "path": "/", "sameSite": "Lax", "secure": false, "value": "5"}, {"domain": ".bilibili.com", "expiry": 1720663600, "httpOnly": false, "name": "CURRENT_FNVAL", "path": "/", "sameSite": "Lax", "secure": false, "value": "4048"}, {"domain": ".bilibili.com", "expiry": 1720663579, "httpOnly": false, "name": "buvid3", "path": "/", "sameSite": "Lax", "secure": false, "value": "088CC37C-ED66-8EBC-052C-D01F7AD3CCFB80244infoc"}, {"domain": ".bilibili.com", "expiry": 1720663579, "httpOnly": false, "name": "_uuid", "path": "/", "sameSite": "Lax", "secure": false, "value": "219FD84B-110C9-52EE-85DF-B469E798236679704infoc"}, {"domain": ".bilibili.com", "expiry": 1704679591, "httpOnly": false, "name": "bili_jct", "path": "/", "sameSite": "Lax", "secure": false, "value": "8f7d6b561391d08e3d2f327621f180e8"}, {"domain": ".bilibili.com", "expiry": 1720663579, "httpOnly": false, "name": "i-wanna-go-back", "path": "/", "sameSite": "Lax", "secure": false, "value": "-1"}, {"domain": ".bilibili.com", "expiry": 1720663579, "httpOnly": false, "name": "b_ut", "path": "/", "sameSite": "Lax", "secure": false, "value": "7"}, {"domain": ".bilibili.com", "httpOnly": false, "name": "b_lsid", "path": "/", "sameSite": "Lax", "secure": false, "value": "7DEABAF7_18947D9702C"}, {"domain": ".bilibili.com", "httpOnly": false, "name": "innersign", "path": "/", "sameSite": "Lax", "secure": false, "value": "0"}]